<navigation>
	<model action="index.php" droits="gestion" retourko="model" retourlogin="1"
		retourok="model" loginrequis="1" 
		 param="param1" type="html|ajax|pdf|csv" droitko="droitko" modulebefore="module1,module2">
	</model>
	<default action="framework/default.php" type="smarty" ></default>
	<droitko action="framework/droitko.php" type="smarty" ></droitko>
	<droits menudroits="admin" droits="admin" menulevel="0" menuorder="7" menuvalue="14" menutitle="15" />
	<gestiondroits action="framework/identification/gestiondroits.php" droits="admin" loginrequis="0" retourlogin="1" droitko="droitko"/>
	
	<loginList action="framework/identification/login.php" param="list" droits="admin" retourlogin="1"  type="smarty" />
	<loginChange action="framework/identification/login.php" param="change" droits="admin"  type="smarty" />
	<loginWrite action="framework/identification/login.php" param="write" droits="admin" retourko="loginChange" retourok="loginList" modulebefore="loginChange" />
	<loginDelete action="framework/identification/login.php" param="delete" droits="admin" retourko="loginChange" retourok="loginList" modulebefore="loginChange"/>
	<loginChangePassword action="framework/identification/login.php" param="changePassword" loginrequis="1"  type="smarty" />
	<loginChangePasswordExec action="framework/identification/login.php" param="changePasswordExec" loginrequis="1" retourko="loginChangePassword" retourok="default" modulebefore="loginChangePassword" />

	<administration action="modules/administration/index.php" droits="admin"
		retourko="" retourok="" retournull="" droitko="droitko" type="smarty" ></administration>
	<gestion action="modules/gestion/index.php" droits="gestion" retourko=""
		retourok="" droitko="droitko" type="smarty" >
	</gestion>
	<errorbefore action="framework/errorbefore.php" retourlogin="1"  type="smarty" ></errorbefore>
	<errorlogin action="framework/errorlogin.php" retourlogin="1" type="smarty"  ></errorlogin>

	<connexion loginrequis="1"  type="smarty" />
	<disconnect action="framework/identification/disconnect.php"  type="smarty" />
	<phpinfo action="framework/phpinfo.php" droits="admin" retourlogin="1" type="smarty"  />
	<aide action="framework/apropos.php" type="smarty" />
	<apropos action="framework/apropos.php" type="smarty"  />
	<quoideneuf action="doc/quoideneuf.php"  retourlogin="1"  type="smarty" />
	<setlanguage action='framework/setlanguage.php' param="" retourlogin="1" type="smarty" retourok="default"  />
	<setlanguagefr action='framework/setlanguage.php' param="fr" retourlogin="1" type="smarty" retourok="default" />
	<setlanguageen action='framework/setlanguage.php' param="en" retourlogin="1" type="smarty" retourok="default" />
	
<!-- gestion des droits nouvelle formule -->
	<appliList action="framework/droits/appli.php" param="list" droits="admin" retourlogin="1"  type="smarty"  />
	<appliDisplay action="framework/droits/appli.php" param="display" droits="admin" type="smarty"  />
	<appliChange action="framework/droits/appli.php" param="change" droits="admin" type="smarty"  />
	<appliWrite action="framework/droits/appli.php" param="write" droits="admin" retourok="appliDisplay" retourko="appliChange" modulebefore="appliChange" />
	<appliDelete action="framework/droits/appli.php" param="delete" droits="admin" retourok="appliList" retourko="appliChange"  modulebefore="appliChange"/>

	<aclloginList action="framework/droits/login.php" param="list" droits="admin" retourlogin="1"  type="smarty" />
	<aclloginChange action="framework/droits/login.php" param="change" droits="admin"  type="smarty" />
	<aclloginWrite action="framework/droits/login.php" param="write" droits="admin" retourok="aclloginList" retourko="aclloginChange" modulebefore="aclloginChange" />
	<aclloginDelete action="framework/droits/login.php" param="delete" droits="admin" retourok="aclloginList" retourko="aclloginChange"  modulebefore="aclloginChange"/>

	<groupList action="framework/droits/group.php" param="list" droits="admin" retourlogin="1"  type="smarty"  />
	<groupChange action="framework/droits/group.php" param="change" droits="admin" type="smarty"  />
	<groupWrite action="framework/droits/group.php" param="write" droits="admin" retourok="groupList" retourko="groupChange" modulebefore="groupChange" />
	<groupDelete action="framework/droits/group.php" param="delete" droits="admin" retourok="groupList" retourko="groupChange"  modulebefore="groupChange"/>

	<acoDisplay action="framework/droits/aco.php" param="display" droits="admin" type="smarty"  />
	<acoChange action="framework/droits/aco.php" param="change" droits="admin"  type="smarty" />
	<acoWrite action="framework/droits/aco.php" param="write" droits="admin" retourok="appliDisplay" retourko="acoChange" modulebefore="acoChange" />
	<acoDelete action="framework/droits/aco.php" param="delete" droits="admin" retourok="appliDisplay" retourko="acoChange"  modulebefore="acoChange"/>

	<passwordlostIslost action="framework/identification/passwordLost.php" param="isLost" type="smarty"/>
	<passwordlostSendmail action="framework/identification/passwordLost.php" param="sendMail" retourok="default"/>
	<passwordlostReinitchange action="framework/identification/passwordLost.php" param="reinitChange" type="smarty" />
	<passwordlostReinitwrite action="framework/identification/passwordLost.php" param="reinitWrite" modulebefore="passwordlostReinitchange" retourko="default" retourok="connexion"/>

<!-- Modules specifiques de l'application -->
	<parametre droits="consult" type="smarty" />
	<eventTypeList action="modules/param/eventType.php" param="list" droits="consult"  retourlogin="1" type="smarty" />
	<eventTypeChange action="modules/param/eventType.php" param="change" droits="param"  retourlogin="1" type="smarty" />
	<eventTypeWrite action="modules/param/eventType.php" param="write" droits="param" retourok="eventTypeList" retourko="eventTypeChange" modulebefore="eventTypeChange" />
	<eventTypeDelete action="modules/param/eventType.php" param="delete" droits="param" retourok="eventTypeList" retourko="eventTypeChange"  modulebefore="eventTypeChange"/>

	<containerFamilyList action="modules/param/containerFamily.php" param="list" droits="consult" retourlogin="1" type="smarty"  />
	<containerFamilyChange action="modules/param/containerFamily.php" param="change" droits="param,projet"  retourlogin="1" type="smarty" />
	<containerFamilyWrite action="modules/param/containerFamily.php" param="write" droits="param,projet" retourok="containerFamilyList" retourko="containerFamilyChange" modulebefore="containerFamilyChange" />
	<containerFamilyDelete action="modules/param/containerFamily.php" param="delete" droits="param,projet" retourok="containerFamilyList" retourko="containerFamilyChange"  modulebefore="containerFamilyChange"/>

	<objectStatusList action="modules/param/objectStatus.php" param="list" droits="consult"  retourlogin="1" type="smarty" />
	<objectStatusChange action="modules/param/objectStatus.php" param="change" droits="param"  retourlogin="1" type="smarty" />
	<objectStatusWrite action="modules/param/objectStatus.php" param="write" droits="param" retourok="objectStatusList" retourko="objectStatusChange" modulebefore="objectStatusChange" />
	<objectStatusDelete action="modules/param/objectStatus.php" param="delete" droits="param" retourok="objectStatusList" retourko="objectStatusChange"  modulebefore="objectStatusChange"/>

	<storageConditionList action="modules/param/storageCondition.php" param="list" droits="consult"  retourlogin="1" type="smarty" />
	<storageConditionChange action="modules/param/storageCondition.php" param="change" droits="param,projet"  retourlogin="1" type="smarty" />
	<storageConditionWrite action="modules/param/storageCondition.php" param="write" droits="param,projet" retourok="storageConditionList" retourko="storageConditionChange" modulebefore="storageConditionChange" />
	<storageConditionDelete action="modules/param/storageCondition.php" param="delete" droits="param,projet" retourok="storageConditionList" retourko="storageConditionChange"  modulebefore="storageConditionChange"/>

	<containerTypeList action="modules/param/containerType.php" param="list" droits="consult"  retourlogin="1" type="smarty" />
	<containerTypeChange action="modules/param/containerType.php" param="change" droits="param,projet"  retourlogin="1" type="smarty" />
	<containerTypeWrite action="modules/param/containerType.php" param="write" droits="param,projet" retourok="containerTypeList" retourko="containerTypeChange" modulebefore="containerTypeChange" />
	<containerTypeDelete action="modules/param/containerType.php" param="delete" droits="param,projet" retourok="containerTypeList" retourko="containerTypeChange"  modulebefore="containerTypeChange"/>
	<containerTypeGetFromFamily action="modules/param/containerType.php" param="getFromFamily" droits="consult"  type="ajax" />
	
	<sampleTypeList action="modules/param/sampleType.php" param="list" droits="consult"  retourlogin="1" type="smarty" />
	<sampleTypeChange action="modules/param/sampleType.php" param="change" droits="param,projet"  retourlogin="1" type="smarty" />
	<sampleTypeWrite action="modules/param/sampleType.php" param="write" droits="param,projet" retourok="sampleTypeList" retourko="sampleTypeChange" modulebefore="sampleTypeChange" />
	<sampleTypeDelete action="modules/param/sampleType.php" param="delete" droits="param,projet" retourok="sampleTypeList" retourko="sampleTypeChange"  modulebefore="sampleTypeChange"/>
	<sampleTypeMetadata action="modules/param/sampleType.php" param="metadata" droits="consult" type="ajax"/>

	<storageReasonList action="modules/param/storageReason.php" param="list" droits="consult" retourlogin="1" type="smarty"  />
	<storageReasonChange action="modules/param/storageReason.php" param="change" droits="param,projet"  retourlogin="1" type="smarty" />
	<storageReasonWrite action="modules/param/storageReason.php" param="write" droits="param,projet" retourok="storageReasonList" retourko="storageReasonChange" modulebefore="storageReasonChange" />
	<storageReasonDelete action="modules/param/storageReason.php" param="delete" droits="param,projet" retourok="storageReasonList" retourko="storageReasonChange"  modulebefore="storageReasonChange"/>
	

	<gestion droits="consult"/>
	<containerList action="modules/gestion/container.php" param="list" droits="consult" retourlogin="1"  type="smarty"  />
	<containerDisplay action="modules/gestion/container.php" param="display" droits="consult"  retourlogin="1" type="smarty" />
	<containerChange action="modules/gestion/container.php" param="change" droits="gestion"  retourlogin="1" type="smarty" />
	<containerWrite action="modules/gestion/container.php" param="write" droits="gestion" retourok="containerDisplay" retourko="containerChange" modulebefore="containerChange" />
	<containerDelete action="modules/gestion/container.php" param="delete" droits="gestion" retourok="containerList" retourko="containerChange"  modulebefore="containerChange"/>
	<containerGetFromType action="modules/gestion/container.php" param="getFromType" droits="consult"  type="ajax" />
	<containerGetFromUid action="modules/gestion/container.php" param="getFromUid" droits="consult"  type="ajax" />

	<containereventChange action="modules/gestion/event.php" param="change" droits="gestion" retourlogin="1" type="smarty" />
	<containereventWrite action="modules/gestion/event.php" param="write" droits="gestion"  retourok="containerDisplay" retourko="containereventChange" modulebefore="containereventChange" />
	<containereventDelete action="modules/gestion/event.php" param="delete" droits="gestion"  retourok="containerDisplay" retourko="containereventChange" modulebefore="containereventChange"/>
	<sampleeventChange action="modules/gestion/event.php" param="change" droits="gestion"  retourlogin="1" type="smarty"  />
	<sampleeventWrite action="modules/gestion/event.php" param="write" droits="gestion"  retourok="sampleDisplay" retourko="sampleeventChange" modulebefore="sampleeventChange" />
	<sampleeventDelete action="modules/gestion/event.php" param="delete" droits="gestion"  retourok="sampleDisplay" retourko="sampleeventChange" modulebefore="sampleeventChange"/>

	<storagecontainerInput action="modules/gestion/storage.php" param="input" droits="gestion"  retourlogin="1" type="smarty" />
	<storagecontainerOutput action="modules/gestion/storage.php" param="output" droits="gestion"  retourlogin="1" type="smarty" />	
	<storagecontainerWrite action="modules/gestion/storage.php" param="write" droits="gestion"  retourok="containerDisplay" retourko="containerDisplay" modulebefore="storagecontainerInput,storagecontainerOutput" />
	<storagecontainerDelete action="modules/gestion/storage.php" param="delete" droits="gestion"  retourok="containerDisplay" retourko="containerDisplay" modulebefore="storagecontainerInput,storagecontainerOutput"/>
	<storagesampleInput action="modules/gestion/storage.php" param="input" droits="gestion"  retourlogin="1" type="smarty" />
	<storagesampleOutput action="modules/gestion/storage.php" param="output" droits="gestion"  retourlogin="1" type="smarty" />	
	<storagesampleWrite action="modules/gestion/storage.php" param="write" droits="gestion"  retourok="sampleDisplay" retourko="sampleDisplay" modulebefore="storagesampleInput,storagesampleOutput" />
	<storagesampleDelete action="modules/gestion/storage.php" param="delete" droits="gestion"  retourok="sampleDisplay" retourko="sampleDisplay" modulebefore="storagesampleInput,storagesampleOutput"/>
	
	<projectList action="modules/param/project.php" param="list" droits="consult"  retourlogin="1" type="smarty" />
	<projectChange action="modules/param/project.php" param="change" droits="param"  retourlogin="1" type="smarty" />
	<projectWrite action="modules/param/project.php" param="write" droits="param" retourok="projectList" retourko="projectChange" modulebefore="projectChange" />
	<projectDelete action="modules/param/project.php" param="delete" droits="param" retourok="projectList" retourko="projectChange"  modulebefore="projectChange"/>

	<labelList action="modules/param/label.php" param="list" droits="consult"  retourlogin="1" type="smarty" />
	<labelChange action="modules/param/label.php" param="change" droits="projet"  retourlogin="1" type="smarty" />
	<labelWrite action="modules/param/label.php" param="write" droits="projet" retourok="labelList" retourko="labelChange" modulebefore="labelChange,labelCopy" />
	<labelDelete action="modules/param/label.php" param="delete" droits="projet" retourok="labelList" retourko="labelChange"  modulebefore="labelChange"/>
	<labelCopy action="modules/param/label.php" param="copy" droits="projet" type="smarty" />
	
	<metadataFormGetDetail action="modules/param/sampleType.php" param="getDetailFormAjax"  droits="consult"  type="ajax" />
	<sampleList action="modules/gestion/sample.php" param="list" droits="consult" retourlogin="1"  type="smarty"  />
	<sampleDisplay action="modules/gestion/sample.php" param="display" droits="consult"  retourlogin="1" type="smarty" />
	<sampleChange action="modules/gestion/sample.php" param="change" droits="gestion"  retourlogin="1" type="smarty" />
	<sampleWrite action="modules/gestion/sample.php" param="write" droits="gestion" retourok="sampleDisplay" retourko="sampleChange" modulebefore="sampleChange" />
	<sampleDelete action="modules/gestion/sample.php" param="delete" droits="gestion" retourok="sampleList" retourko="sampleChange"  modulebefore="sampleChange"/>
	
	<storage droits="consult" type="smarty" />
	<objets retourlogin="1" type="smarty" />
	<fastInputChange action="modules/gestion/storage.php" param="fastInputChange" droits="gestion"  retourlogin="1" type="smarty" />
	<fastInputWrite action="modules/gestion/storage.php" param="fastInputWrite" droits="gestion" retourok="fastInputChange" retourko="fastInputChange" modulebefore="fastInputChange" />
	<fastOutputChange action="modules/gestion/storage.php" param="fastOutputChange" droits="gestion"  retourlogin="1" type="smarty" />
	<fastOutputWrite action="modules/gestion/storage.php" param="fastOutputWrite" droits="gestion" retourok="fastOutputChange" retourko="fastOutputChange" modulebefore="fastOutputChange" />
	
	<objectGetDetail droits="consult" action="modules/gestion/object.php" param="getDetailAjax"  type="ajax" />
	<containerPrintLabel droits="gestion" action="modules/gestion/object.php" param="printLabel" type="pdf" retourko="containerList"/>
	<containerExportCSV droits="gestion" action="modules/gestion/object.php" param="exportCSV" type="csv" retourko="containerList"/>
	<containerPrintDirect droits="gestion" action="modules/gestion/object.php" param="printLabelDirect" type="printdirect" retourko="containerList"/>
	<samplePrintLabel droits="gestion" action="modules/gestion/object.php" param="printLabel" type="pdf" retourko="sampleList"/>
	<sampleExportCSV droits="gestion" action="modules/gestion/object.php" param="exportCSV" type="csv" retourko="sampleList"/>
	<samplePrintDirect droits="gestion" action="modules/gestion/object.php" param="printLabelDirect" type="printdirect" retourko="sampleList"/>
	
	<importChange action="modules/gestion/import.php" param="change" droits="projet" retourlogin="1"  type="smarty" />
	<importControl action="modules/gestion/import.php" param="control" droits="projet" modulebefore="importChange,importControl,importImport" retourok="importChange"  type="smarty" />
	<importImport action="modules/gestion/import.php" param="import" droits="projet" modulebefore="importControl,importChange" retourok="importChange" retourko="importChange" type="smarty" />

	<containerbookingChange action="modules/gestion/booking.php" param="change" droits="gestion" retourlogin="1" type="smarty" />
	<containerbookingWrite action="modules/gestion/booking.php" param="write" droits="gestion"  retourok="containerDisplay" retourko="containerbookingChange" modulebefore="containerbookingChange" />
	<containerbookingDelete action="modules/gestion/booking.php" param="delete" droits="gestion"  retourok="containerDisplay" retourko="containerbookingChange" modulebefore="containerbookingChange"/>
	<samplebookingChange action="modules/gestion/booking.php" param="change" droits="gestion"  retourlogin="1" type="smarty"  />
	<samplebookingWrite action="modules/gestion/booking.php" param="write" droits="gestion"  retourok="sampleDisplay" retourko="samplebookingChange" modulebefore="samplebookingChange" />
	<samplebookingDelete action="modules/gestion/booking.php" param="delete" droits="gestion"  retourok="sampleDisplay" retourko="samplebookingChange" modulebefore="samplebookingChange"/>
	<bookingVerifyInterval action="modules/gestion/booking.php" param="verifyInterval" droits="gestion" type="ajax" />
	
	<protocolList action="modules/param/protocol.php" param="list" droits="consult"  retourlogin="1" type="smarty" />
	<protocolChange action="modules/param/protocol.php" param="change" droits="projet"  retourlogin="1" type="smarty" />
	<protocolWrite action="modules/param/protocol.php" param="write" droits="projet" retourok="protocolList" retourko="protocolChange" modulebefore="protocolChange" />
	<protocolDelete action="modules/param/protocol.php" param="delete" droits="projet" retourok="protocolList" retourko="protocolChange"  modulebefore="protocolChange"/>
	<protocolFile action="modules/param/protocol.php" param="file" droits="consult" type="pdf" retourko="protocolList"/>

	<operationList action="modules/param/operation.php" param="list" droits="consult"  retourlogin="1" type="smarty" />
	<operationChange action="modules/param/operation.php" param="change" droits="projet"  retourlogin="1" type="smarty" />
	<operationCopy action="modules/param/operation.php" param="copy" droits="projet" type="smarty" />
	<operationWrite action="modules/param/operation.php" param="write" droits="projet" retourok="operationList" retourko="operationChange" modulebefore="operationChange,operationCopy" />
	<operationDelete action="modules/param/operation.php" param="delete" droits="projet" retourok="operationList" retourko="operationChange"  modulebefore="operationChange"/>
	<operationMetadata action="modules/param/operation.php" param="metadata" droits="projet" type="ajax" />
	
	<multipleTypeList action="modules/param/multipleType.php" param="list" droits="consult"  retourlogin="1" type="smarty" />
	<multipleTypeChange action="modules/param/multipleType.php" param="change" droits="param"  retourlogin="1" type="smarty" />
	<multipleTypeWrite action="modules/param/multipleType.php" param="write" droits="param" retourok="multipleTypeList" retourko="multipleTypeChange" modulebefore="multipleTypeChange" />
	<multipleTypeDelete action="modules/param/multipleType.php" param="delete" droits="param" retourok="multipleTypeList" retourko="multipleTypeChange"  modulebefore="multipleTypeChange"/>

	<samplingPlaceList action="modules/param/samplingPlace.php" param="list" droits="consult"  retourlogin="1" type="smarty" />
	<samplingPlaceChange action="modules/param/samplingPlace.php" param="change" droits="param"  retourlogin="1" type="smarty" />
	<samplingPlaceWrite action="modules/param/samplingPlace.php" param="write" droits="param" retourok="samplingPlaceList" retourko="samplingPlaceChange" modulebefore="samplingPlaceChange" />
	<samplingPlaceDelete action="modules/param/samplingPlace.php" param="delete" droits="param" retourok="samplingPlaceList" retourko="samplingPlaceChange"  modulebefore="samplingPlaceChange"/>


	<subsampleChange action="modules/gestion/subsample.php" param="change" droits="gestion"  retourlogin="1" type="smarty"  />
	<subsampleWrite action="modules/gestion/subsample.php" param="write" droits="gestion"  retourok="sampleDisplay" retourko="subsampleChange" modulebefore="subsampleChange" />
	<subsampleDelete action="modules/gestion/subsample.php" param="delete" droits="gestion"  retourok="sampleDisplay" retourko="subsampleChange" modulebefore="subsampleChange"/>

	<containerdocumentWrite action="modules/gestion/document.php" param="write" droits="gestion" retourok="containerDisplay" retourko="containerDisplay" modulebefore="containerDisplay" />
	<containerdocumentDelete action="modules/gestion/document.php" param="delete" droits="gestion" retourok="containerDisplay" retourko="containerDisplay" modulebefore="containerDisplay" />
	<sampledocumentWrite action="modules/gestion/document.php" param="write" droits="gestion" retourok="sampleDisplay" retourko="sampleDisplay" modulebefore="sampleDisplay" />
	<sampledocumentDelete action="modules/gestion/document.php" param="delete" droits="gestion" retourok="sampleDisplay" retourko="sampleDisplay" modulebefore="sampleDisplay" />
	<documentGet action="modules/gestion/document.php" param="get" type="binaire" droits="consult"/>	

	<identifierTypeList action="modules/param/identifierType.php" param="list" droits="consult"  retourlogin="1" type="smarty" />
	<identifierTypeChange action="modules/param/identifierType.php" param="change" droits="param"  retourlogin="1" type="smarty" />
	<identifierTypeWrite action="modules/param/identifierType.php" param="write" droits="param" retourok="identifierTypeList" retourko="identifierTypeChange" modulebefore="identifierTypeChange" />
	<identifierTypeDelete action="modules/param/identifierType.php" param="delete" droits="param" retourok="identifierTypeList" retourko="identifierTypeChange"  modulebefore="identifierTypeChange"/>
	
	<containerobjectIdentifierChange action="modules/gestion/objectIdentifier.php" param="change" droits="gestion" retourlogin="1" type="smarty" />
	<containerobjectIdentifierWrite action="modules/gestion/objectIdentifier.php" param="write" droits="gestion"  retourok="containerDisplay" retourko="containerobjectIdentifierChange" modulebefore="containerobjectIdentifierChange" />
	<containerobjectIdentifierDelete action="modules/gestion/objectIdentifier.php" param="delete" droits="gestion"  retourok="containerDisplay" retourko="containerobjectIdentifierChange" modulebefore="containerobjectIdentifierChange"/>
	<sampleobjectIdentifierChange action="modules/gestion/objectIdentifier.php" param="change" droits="gestion"  retourlogin="1" type="smarty"  />
	<sampleobjectIdentifierWrite action="modules/gestion/objectIdentifier.php" param="write" droits="gestion"  retourok="sampleDisplay" retourko="sampleobjectIdentifierChange" modulebefore="sampleobjectIdentifierChange" />
	<sampleobjectIdentifierDelete action="modules/gestion/objectIdentifier.php" param="delete" droits="gestion"  retourok="sampleDisplay" retourko="sampleobjectIdentifierChange" modulebefore="sampleobjectIdentifierChange"/>
	
	<storageBatchOpen action="modules/gestion/storage.php" param="batchOpen" droits="gestion" type="smarty" retourlogin="1" />
	<storageBatchRead action="modules/gestion/storage.php" param="batchRead" droits="gestion" type="smarty" modulebefore="storageBatchOpen,storageBatchWrite" />
	<storageBatchWrite action="modules/gestion/storage.php" param="batchWrite" droits="gestion" modulebefore="storageBatchRead" retourok="storageBatchOpen" retourko="storageBatchRead" />

	<printerList action="modules/param/printer.php" param="list" droits="consult"  retourlogin="1" type="smarty" />
	<printerChange action="modules/param/printer.php" param="change" droits="param"  retourlogin="1" type="smarty" />
	<printerWrite action="modules/param/printer.php" param="write" droits="param" retourok="printerList" retourko="printerChange" modulebefore="printerChange" />
	<printerDelete action="modules/param/printer.php" param="delete" droits="param" retourok="printerList" retourko="printerChange"  modulebefore="printerChange"/>
	
	
</navigation>
	